NetkillerNetworkFix1/README.md
NetkillerNetworkFix1/__init__.py
NetkillerNetworkFix1/__main__.py
NetkillerNetworkFix1/file.epub
NetkillerNetworkFix1/index.html
NetkillerNetworkFix1/css/__init__.py
NetkillerNetworkFix1/css/annotations.css
NetkillerNetworkFix1/css/main.css
NetkillerNetworkFix1/css/normalize.css
NetkillerNetworkFix1/css/popup.css
NetkillerNetworkFix1/font/__init__.py
NetkillerNetworkFix1/font/fontello.eot
NetkillerNetworkFix1/font/fontello.svg
NetkillerNetworkFix1/font/fontello.ttf
NetkillerNetworkFix1/font/fontello.woff
NetkillerNetworkFix1/img/__init__.py
NetkillerNetworkFix1/img/annotator-glyph-sprite.png
NetkillerNetworkFix1/img/annotator-icon-sprite.png
NetkillerNetworkFix1/img/apple-touch-icon.png
NetkillerNetworkFix1/img/cancelfullscreen.png
NetkillerNetworkFix1/img/close.png
NetkillerNetworkFix1/img/fullscreen.png
NetkillerNetworkFix1/img/loader.gif
NetkillerNetworkFix1/img/menu-icon.png
NetkillerNetworkFix1/img/save.png
NetkillerNetworkFix1/img/saved.png
NetkillerNetworkFix1/img/settings-s.png
NetkillerNetworkFix1/img/settings.png
NetkillerNetworkFix1/img/star.png
NetkillerNetworkFix1/js/__init__.py
NetkillerNetworkFix1/js/epub.js
NetkillerNetworkFix1/js/epub.min.js
NetkillerNetworkFix1/js/epub.min.map
NetkillerNetworkFix1/js/hooks.min.js
NetkillerNetworkFix1/js/hooks.min.map
NetkillerNetworkFix1/js/reader.js
NetkillerNetworkFix1/js/reader.js.map
NetkillerNetworkFix1/js/reader.min.js
NetkillerNetworkFix1/js/reader.min.map
NetkillerNetworkFix1/js/hooks/__init__.py
NetkillerNetworkFix1/js/hooks/extensions/__init__.py
NetkillerNetworkFix1/js/hooks/extensions/highlight.js
NetkillerNetworkFix1/js/libs/__init__.py
NetkillerNetworkFix1/js/libs/jquery.min.js
NetkillerNetworkFix1/js/libs/localforage.min.js
NetkillerNetworkFix1/js/libs/screenfull.js
NetkillerNetworkFix1/js/libs/screenfull.min.js
NetkillerNetworkFix1/js/libs/zip.min.js
NetkillerNetworkFix1/js/plugins/__init__.py
NetkillerNetworkFix1/js/plugins/hypothesis.js
netkiller_network_fix1-2025.3.24.1.dist-info/METADATA
netkiller_network_fix1-2025.3.24.1.dist-info/WHEEL
netkiller_network_fix1-2025.3.24.1.dist-info/entry_points.txt
netkiller_network_fix1-2025.3.24.1.dist-info/top_level.txt
netkiller_network_fix1-2025.3.24.1.dist-info/RECORD
